dbus_mediaplayer/__init__.py
dbus_mediaplayer/__main__.py
dbus_mediaplayer-2025.6.0.dist-info/LICENSE.md
dbus_mediaplayer-2025.6.0.dist-info/METADATA
dbus_mediaplayer-2025.6.0.dist-info/WHEEL
dbus_mediaplayer-2025.6.0.dist-info/entry_points.txt
dbus_mediaplayer-2025.6.0.dist-info/top_level.txt
dbus_mediaplayer-2025.6.0.dist-info/RECORD
