Metadata-Version: 2.1
Name: dbus_mediaplayer
Version: 2025.6.0
Summary: Currently playng media using DBus
Author-email: bkbilly <bkbilly@hotmail.com>
Project-URL: Source Code, https://github.com/bkbilly/dbus_mediaplayer
Keywords: lnxlink
Classifier: Programming Language :: Python :: 3
Classifier: License :: OSI Approved :: MIT License
Classifier: Operating System :: Unix
Requires-Python: >=3.7.0
License-File: LICENSE.md
Requires-Dist: jeepney >=0.9.0
